Workbook

Sheet Summary
A1: Haverton Recruitment: Year 1 summary
A2: ="Case shown: "&Assumptions!$C$3&" (change on the Assumptions sheet)" -> Case shown: Cautious (change on the Assumptions sheet)
A4: Measure | B4: Year 1
A5: Total revenue | B5: ='Year 1 Monthly'!N13 -> 98000
A6: Gross profit | B6: ='Year 1 Monthly'!N15 -> 90320
A7: Gross margin | B7: ='Year 1 Monthly'!N16 -> 0.92163265
A8: Operating costs | B8: ='Year 1 Monthly'!N17 -> 18000
A9: Profit before tax (EBITDA) | B9: ='Year 1 Monthly'!N18 -> 72320
A10: Permanent placements | B10: ='Year 1 Monthly'!N5 -> 12
A11: VAT | B11: ='Year 1 Monthly'!B22 -> Yes: register for VAT (check timing with accountant)
A12: Temp GP per hour check | B12: =Assumptions!F26 -> OK
A14: Base case Years 2 and 3 (targets from Financial Model v2.0): revenue £2,563,380 and £5,414,240; gross profit £1,055,634 and £1,996,879. Driven mainly by temporary staffing, which starts only after the Go Live Gate.
A15: These are forecasts and targets, not promises or results. Review with your accountant.

Sheet Assumptions
A1: Haverton Recruitment Forecast
A2: Year 1 = October 2026 to September 2027. Blue = inputs you can change. Yellow = choose the case. All values exclude VAT. Targets, not promises.
A3: Case to show | C3: Cautious | D3: Choose Cautious or Base
A5: Assumption | B5: Unit | C5: Cautious | D5: Base | E5: Source or note | F5: Selected
A6: Average permanent fee | B6: £ per placement | C6: 5500 | D6: 7500 | E6: Cautious: planning assumption. Base: Financial Model v2.0 | F6: =IF($C$3="Base",D6,C6) -> 5500
A7: Average retained search fee | B7: £ per search | C7: 10000 | D7: 12000 | E7: Cautious: assumption. Base: Financial Model v2.0 | F7: =IF($C$3="Base",D7,C7) -> 10000
A8: Average compliance project fee | B8: £ per project | C8: 1500 | D8: 1500 | E8: Financial Model v2.0 [confirm per scope] | F8: =IF($C$3="Base",D8,C8) -> 1500
A9: Temp hours per worker per week | B9: hours | C9: 30 | D9: 30 | E9: Financial Model v2.0 | F9: =IF($C$3="Base",D9,C9) -> 30
A10: Temp charge rate | B10: £ per hour | C10: 26 | D10: 26 | E10: Financial Model v2.0, ex VAT | F10: =IF($C$3="Base",D10,C10) -> 26
A11: Temp basic pay | B11: £ per hour | C11: 14.5 | D11: 14.5 | E11: Must stay at or above National Living Wage (£12.71, 21+, from April 2026) | F11: =IF($C$3="Base",D11,C11) -> 14.5
A12: Holiday pay load | B12: % of pay | C12: 0.1207 | D12: 0.1207 | E12: Planning load; confirm payroll method | F12: =IF($C$3="Base",D12,C12) -> 0.1207
A13: Employer NI load (blended) | B13: % of pay | C13: 0.105 | D13: 0.105 | E13: Planning proxy; statutory rate is 15% above threshold | F13: =IF($C$3="Base",D13,C13) -> 0.105
A14: Pension load (blended) | B14: % of pay | C14: 0.025 | D14: 0.025 | E14: Planning proxy | F14: =IF($C$3="Base",D14,C14) -> 0.025
A15: Other temp direct cost | B15: £ per hour | C15: 0.75 | D15: 0.75 | E15: Payroll, compliance, insurance allocation | F15: =IF($C$3="Base",D15,C15) -> 0.75
A16: Bad debt allowance | B16: % of temp billings | C16: 0.01 | D16: 0.01 | E16: Financial Model v2.0 | F16: =IF($C$3="Base",D16,C16) -> 0.01
A17: Permanent direct cost | B17: % of fee | C17: 0.08 | D17: 0.08 | E17: Job boards, checks | F17: =IF($C$3="Base",D17,C17) -> 0.08
... A21: VAT registration threshold | B21: £ taxable turnover | C21: 90000 | D21: 90000 | E21: GOV.UK [confirm current] | F21: =IF($C$3="Base",D21,C21) -> 90000
A24: Loaded temp cost per hour | F24: =F11*(1+F12+F13+F14)+F15 -> 18.88515
A25: Temp gross profit per hour (after bad debt) | F25: =F10-F24-F10*F16 -> 6.85485
A26: Floor check (target at least £5.50) | F26: =IF(F25>=5.5,"OK","Below floor") -> OK

Sheet Volumes
A1: Monthly volumes by case
A2: Blue = inputs. Base case from Financial Model v2.0. Cautious case is a founder-only planning assumption with no temporary staffing in Year 1.
A4: Cautious case
A5: Line | B5: Oct 26 | C5: Nov 26 | D5: Dec 26 | E5: Jan 27 | F5: Feb 27 | G5: Mar 27 | H5: Apr 27 | I5: May 27 | J5: Jun 27 | K5: Jul 27 | L5: Aug 27 | M5: Sep 27
A6: Permanent placements | B6: 0 | C6: 0 | D6: 1 | E6: 1 | F6: 1 | G6: 1 | H6: 1 | I6: 1 | J6: 1 | K6: 2 | L6: 1 | M6: 2
A7: Retained searches | B7: 0 | C7: 0 | D7: 0 | E7: 0 | F7: 0 | G7: 1 | H7: 0 | I7: 0 | J7: 0 | K7: 0 | L7: 1 | M7: 0
A8: Compliance projects | B8: 0 | C8: 1 | D8: 0 | E8: 1 | F8: 1 | G8: 1 | H8: 0 | I8: 1 | J8: 1 | K8: 1 | L8: 0 | M8: 1
A9: Active temp workers | B9: 0 | C9: 0 | D9: 0 | E9: 0 | F9: 0 | G9: 0 | H9: 0 | I9: 0 | J9: 0 | K9: 0 | L9: 0 | M9: 0
A10: Operating costs (£) | B10: 1500 | C10: 1500 | D10: 1500 | E10: 1500 | F10: 1500 | G10: 1500 | H10: 1500 | I10: 1500 | J10: 1500 | K10: 1500 | L10: 1500 | M10: 1500
A12: Base case
A13: Line | B13: Oct 26 | C13: Nov 26 | D13: Dec 26 | E13: Jan 27 | F13: Feb 27 | G13: Mar 27 | H13: Apr 27 | I13: May 27 | J13: Jun 27 | K13: Jul 27 | L13: Aug 27 | M13: Sep 27
A14: Permanent placements | B14: 0 | C14: 1 | D14: 1 | E14: 1 | F14: 2 | G14: 2 | H14: 2 | I14: 3 | J14: 3 | K14: 3 | L14: 4 | M14: 4
A15: Retained searches | B15: 0 | C15: 0 | D15: 0 | E15: 0 | F15: 0.5 | G15: 0.5 | H15: 0.5 | I15: 0.5 | J15: 1 | K15: 1 | L15: 1 | M15: 1
A16: Compliance projects | B16: 0 | C16: 1 | D16: 1 | E16: 1 | F16: 1 | G16: 2 | H16: 2 | I16: 2 | J16: 2 | K16: 3 | L16: 3 | M16: 3
A17: Active temp workers | B17: 0 | C17: 0 | D17: 0 | E17: 0 | F17: 0 | G17: 0 | H17: 3 | I17: 6 | J17: 10 | K17: 14 | L17: 18 | M17: 22
A18: Operating costs (£) | B18: 4500 | C18: 5000 | D18: 5500 | E18: 7500 | F18: 10000 | G18: 11500 | H18: 14500 | I18: 17000 | J18: 19500 | K18: 22000 | L18: 24500 | M18: 27000
A20: Cautious operating costs of £1,500 a month are an assumption (insurance, accountant, marketing, phone). They do not include any salary or drawings for the founder. Confirm with your accountant.

Sheet Year 1 Monthly
A1: Year 1 monthly forecast (selected case)
A2: ="Showing: "&Assumptions!$C$3&" case. Change it on the Assumptions sheet." -> Showing: Cautious case. Change it on the Assumptions sheet.
A4: Line | B4: Oct 26 | C4: Nov 26 | D4: Dec 26 | E4: Jan 27 | F4: Feb 27 | G4: Mar 27 | H4: Apr 27 | I4: May 27 | J4: Jun 27 | K4: Jul 27 | L4: Aug 27 | M4: Sep 27 | N4: Year 1
A5: Permanent placements | B5: =IF(Assumptions!$C$3="Base",Volumes!B14,Volumes!B6) -> 0 | C5: =IF(Assumptions!$C$3="Base",Volumes!C14,Volumes!C6) -> 0 | D5: =IF(Assumptions!$C$3="Base",Volumes!D14,Volumes!D6) -> 1 | E5: =IF(Assumptions!$C$3="Base",Volumes!E14,Volumes!E6) -> 1 | F5: =IF(Assumptions!$C$3="Base",Volumes!F14,Volumes!F6) -> 1 | G5: =IF(Assumptions!$C$3="Base",Volumes!G14,Volumes!G6) -> 1 | H5: =IF(Assumptions!$C$3="Base",Volumes!H14,Volumes!H6) -> 1 | I5: =IF(Assumptions!$C$3="Base",Volumes!I14,Volumes!I6) -> 1 | ... M5: =IF(Assumptions!$C$3="Base",Volumes!M14,Volumes!M6) -> 2 | N5: =SUM(B5:M5) -> 12
A6: Retained searches | B6: =IF(Assumptions!$C$3="Base",Volumes!B15,Volumes!B7) -> 0 | C6: =IF(Assumptions!$C$3="Base",Volumes!C15,Volumes!C7) -> 0 | D6: =IF(Assumptions!$C$3="Base",Volumes!D15,Volumes!D7) -> 0 | E6: =IF(Assumptions!$C$3="Base",Volumes!E15,Volumes!E7) -> 0 | F6: =IF(Assumptions!$C$3="Base",Volumes!F15,Volumes!F7) -> 0 | G6: =IF(Assumptions!$C$3="Base",Volumes!G15,Volumes!G7) -> 1 | H6: =IF(Assumptions!$C$3="Base",Volumes!H15,Volumes!H7) -> 0 | I6: =IF(Assumptions!$C$3="Base",Volumes!I15,Volumes!I7) -> 0 | ... M6: =IF(Assumptions!$C$3="Base",Volumes!M15,Volumes!M7) -> 0 | N6: =SUM(B6:M6) -> 2
A7: Compliance projects | B7: =IF(Assumptions!$C$3="Base",Volumes!B16,Volumes!B8) -> 0 | C7: =IF(Assumptions!$C$3="Base",Volumes!C16,Volumes!C8) -> 1 | D7: =IF(Assumptions!$C$3="Base",Volumes!D16,Volumes!D8) -> 0 | E7: =IF(Assumptions!$C$3="Base",Volumes!E16,Volumes!E8) -> 1 | F7: =IF(Assumptions!$C$3="Base",Volumes!F16,Volumes!F8) -> 1 | G7: =IF(Assumptions!$C$3="Base",Volumes!G16,Volumes!G8) -> 1 | H7: =IF(Assumptions!$C$3="Base",Volumes!H16,Volumes!H8) -> 0 | I7: =IF(Assumptions!$C$3="Base",Volumes!I16,Volumes!I8) -> 1 | ... M7: =IF(Assumptions!$C$3="Base",Volumes!M16,Volumes!M8) -> 1 | N7: =SUM(B7:M7) -> 8
A8: Active temp workers | B8: =IF(Assumptions!$C$3="Base",Volumes!B17,Volumes!B9) -> 0 | C8: =IF(Assumptions!$C$3="Base",Volumes!C17,Volumes!C9) -> 0 | D8: =IF(Assumptions!$C$3="Base",Volumes!D17,Volumes!D9) -> 0 | E8: =IF(Assumptions!$C$3="Base",Volumes!E17,Volumes!E9) -> 0 | F8: =IF(Assumptions!$C$3="Base",Volumes!F17,Volumes!F9) -> 0 | G8: =IF(Assumptions!$C$3="Base",Volumes!G17,Volumes!G9) -> 0 | H8: =IF(Assumptions!$C$3="Base",Volumes!H17,Volumes!H9) -> 0 | I8: =IF(Assumptions!$C$3="Base",Volumes!I17,Volumes!I9) -> 0 | ... M8: =IF(Assumptions!$C$3="Base",Volumes!M17,Volumes!M9) -> 0 | N8: =SUM(B8:M8) -> 0
A9: Permanent revenue | B9: =B5*Assumptions!$F$6 -> 0 | C9: =C5*Assumptions!$F$6 -> 0 | D9: =D5*Assumptions!$F$6 -> 5500 | E9: =E5*Assumptions!$F$6 -> 5500 | F9: =F5*Assumptions!$F$6 -> 5500 | G9: =G5*Assumptions!$F$6 -> 5500 | H9: =H5*Assumptions!$F$6 -> 5500 | I9: =I5*Assumptions!$F$6 -> 5500 | ... M9: =M5*Assumptions!$F$6 -> 11000 | N9: =SUM(B9:M9) -> 66000
A10: Retained revenue | B10: =B6*Assumptions!$F$7 -> 0 | C10: =C6*Assumptions!$F$7 -> 0 | D10: =D6*Assumptions!$F$7 -> 0 | E10: =E6*Assumptions!$F$7 -> 0 | F10: =F6*Assumptions!$F$7 -> 0 | G10: =G6*Assumptions!$F$7 -> 10000 | H10: =H6*Assumptions!$F$7 -> 0 | I10: =I6*Assumptions!$F$7 -> 0 | ... M10: =M6*Assumptions!$F$7 -> 0 | N10: =SUM(B10:M10) -> 20000
A11: Project revenue | B11: =B7*Assumptions!$F$8 -> 0 | C11: =C7*Assumptions!$F$8 -> 1500 | D11: =D7*Assumptions!$F$8 -> 0 | E11: =E7*Assumptions!$F$8 -> 1500 | F11: =F7*Assumptions!$F$8 -> 1500 | G11: =G7*Assumptions!$F$8 -> 1500 | H11: =H7*Assumptions!$F$8 -> 0 | I11: =I7*Assumptions!$F$8 -> 1500 | ... M11: =M7*Assumptions!$F$8 -> 1500 | N11: =SUM(B11:M11) -> 12000
A12: Temp revenue | B12: =B8*Assumptions!$F$9*Assumptions!$F$20*Assumptions!$F$10 -> 0 | C12: =C8*Assumptions!$F$9*Assumptions!$F$20*Assumptions!$F$10 -> 0 | D12: =D8*Assumptions!$F$9*Assumptions!$F$20*Assumptions!$F$10 -> 0 | E12: =E8*Assumptions!$F$9*Assumptions!$F$20*Assumptions!$F$10 -> 0 | F12: =F8*Assumptions!$F$9*Assumptions!$F$20*Assumptions!$F$10 -> 0 | G12: =G8*Assumptions!$F$9*Assumptions!$F$20*Assumptions!$F$10 -> 0 | H12: =H8*Assumptions!$F$9*Assumptions!$F$20*Assumptions!$F$10 -> 0 | I12: =I8*Assumptions!$F$9*Assumptions!$F$20*Assumptions!$F$10 -> 0 | ... M12: =M8*Assumptions!$F$9*Assumptions!$F$20*Assumptions!$F$10 -> 0 | N12: =SUM(B12:M12) -> 0
A13: Total revenue | B13: =SUM(B9:B12) -> 0 | C13: =SUM(C9:C12) -> 1500 | D13: =SUM(D9:D12) -> 5500 | E13: =SUM(E9:E12) -> 7000 | F13: =SUM(F9:F12) -> 7000 | G13: =SUM(G9:G12) -> 17000 | H13: =SUM(H9:H12) -> 5500 | I13: =SUM(I9:I12) -> 7000 | ... M13: =SUM(M9:M12) -> 12500 | N13: =SUM(B13:M13) -> 98000
A14: Direct costs | B14: =B9*Assumptions!$F$17+B10*Assumptions!$F$18+B11*Assumptions!$F$19+B8*Assumptions!$F$9*Assumptions!$F$20*(Assumptions!$F$24+Assumptions!$F$10*Assumptions!$F$16) -> 0 | C14: =C9*Assumptions!$F$17+C10*Assumptions!$F$18+C11*Assumptions!$F$19+C8*Assumptions!$F$9*Assumptions!$F$20*(Assumptions!$F$24+Assumptions!$F$10*Assumptions!$F$16) -> 150 | D14: =D9*Assumptions!$F$17+D10*Assumptions!$F$18+D11*Assumptions!$F$19+D8*Assumptions!$F$9*Assumptions!$F$20*(Assumptions!$F$24+Assumptions!$F$10*Assumptions!$F$16) -> 440 | E14: =E9*Assumptions!$F$17+E10*Assumptions!$F$18+E11*Assumptions!$F$19+E8*Assumptions!$F$9*Assumptions!$F$20*(Assumptions!$F$24+Assumptions!$F$10*Assumptions!$F$16) -> 590 | F14: =F9*Assumptions!$F$17+F10*Assumptions!$F$18+F11*Assumptions!$F$19+F8*Assumptions!$F$9*Assumptions!$F$20*(Assumptions!$F$24+Assumptions!$F$10*Assumptions!$F$16) -> 590 | G14: =G9*Assumptions!$F$17+G10*Assumptions!$F$18+G11*Assumptions!$F$19+G8*Assumptions!$F$9*Assumptions!$F$20*(Assumptions!$F$24+Assumptions!$F$10*Assumptions!$F$16) -> 1190 | H14: =H9*Assumptions!$F$17+H10*Assumptions!$F$18+H11*Assumptions!$F$19+H8*Assumptions!$F$9*Assumptions!$F$20*(Assumptions!$F$24+Assumptions!$F$10*Assumptions!$F$16) -> 440 | I14: =I9*Assumptions!$F$17+I10*Assumptions!$F$18+I11*Assumptions!$F$19+I8*Assumptions!$F$9*Assumptions!$F$20*(Assumptions!$F$24+Assumptions!$F$10*Assumptions!$F$16) -> 590 | ... M14: =M9*Assumptions!$F$17+M10*Assumptions!$F$18+M11*Assumptions!$F$19+M8*Assumptions!$F$9*Assumptions!$F$20*(Assumptions!$F$24+Assumptions!$F$10*Assumptions!$F$16) -> 1030 | N14: =SUM(B14:M14) -> 7680
A15: Gross profit | B15: =B13-B14 -> 0 | C15: =C13-C14 -> 1350 | D15: =D13-D14 -> 5060 | E15: =E13-E14 -> 6410 | F15: =F13-F14 -> 6410 | G15: =G13-G14 -> 15810 | H15: =H13-H14 -> 5060 | I15: =I13-I14 -> 6410 | ... M15: =M13-M14 -> 11470 | N15: =SUM(B15:M15) -> 90320
A16: Gross margin | B16: =IF(B13=0,0,B15/B13) -> 0 | C16: =IF(C13=0,0,C15/C13) -> 0.9 | D16: =IF(D13=0,0,D15/D13) -> 0.92 | E16: =IF(E13=0,0,E15/E13) -> 0.91571429 | F16: =IF(F13=0,0,F15/F13) -> 0.91571429 | G16: =IF(G13=0,0,G15/G13) -> 0.93 | H16: =IF(H13=0,0,H15/H13) -> 0.92 | I16: =IF(I13=0,0,I15/I13) -> 0.91571429 | ... N16: =IF(N13=0,0,N15/N13) -> 0.92163265
A17: Operating costs | B17: =IF(Assumptions!$C$3="Base",Volumes!B18,Volumes!B10) -> 1500 | C17: =IF(Assumptions!$C$3="Base",Volumes!C18,Volumes!C10) -> 1500 | D17: =IF(Assumptions!$C$3="Base",Volumes!D18,Volumes!D10) -> 1500 | E17: =IF(Assumptions!$C$3="Base",Volumes!E18,Volumes!E10) -> 1500 | F17: =IF(Assumptions!$C$3="Base",Volumes!F18,Volumes!F10) -> 1500 | G17: =IF(Assumptions!$C$3="Base",Volumes!G18,Volumes!G10) -> 1500 | H17: =IF(Assumptions!$C$3="Base",Volumes!H18,Volumes!H10) -> 1500 | I17: =IF(Assumptions!$C$3="Base",Volumes!I18,Volumes!I10) -> 1500 | ... M17: =IF(Assumptions!$C$3="Base",Volumes!M18,Volumes!M10) -> 1500 | N17: =SUM(B17:M17) -> 18000
A18: Profit before tax (EBITDA) | B18: =B15-B17 -> -1500 | C18: =C15-C17 -> -150 | D18: =D15-D17 -> 3560 | E18: =E15-E17 -> 4910 | F18: =F15-F17 -> 4910 | G18: =G15-G17 -> 14310 | H18: =H15-H17 -> 3560 | I18: =I15-I17 -> 4910 | ... M18: =M15-M17 -> 9970 | N18: =SUM(B18:M18) -> 72320
A19: Cumulative profit | B19: =SUM($B$18:B18) -> -1500 | C19: =SUM($B$18:C18) -> -1650 | D19: =SUM($B$18:D18) -> 1910 | E19: =SUM($B$18:E18) -> 6820 | F19: =SUM($B$18:F18) -> 11730 | G19: =SUM($B$18:G18) -> 26040 | H19: =SUM($B$18:H18) -> 29600 | I19: =SUM($B$18:I18) -> 34510 | ... M19: =SUM($B$18:M18) -> 72320 | N19: =M19 -> 72320
A20: Rolling revenue (VAT watch) | B20: =SUM($B$13:B13) -> 0 | C20: =SUM($B$13:C13) -> 1500 | D20: =SUM($B$13:D13) -> 7000 | E20: =SUM($B$13:E13) -> 14000 | F20: =SUM($B$13:F13) -> 21000 | G20: =SUM($B$13:G13) -> 38000 | H20: =SUM($B$13:H13) -> 43500 | I20: =SUM($B$13:I13) -> 50500 | ... M20: =SUM($B$13:M13) -> 98000 | N20: =M20 -> 98000
A22: VAT threshold passed? | B22: =IF(N20>Assumptions!$F$21,"Yes: register for VAT (check timing with accountant)","Not in Year 1") -> Yes: register for VAT (check timing with accountant)
A23: Temp gross profit per hour | B23: =Assumptions!F25 -> 6.85485
