Workbook

Sheet Inputs
A1: Temporary Staffing Cash Flow (13 weeks)
A2: Haverton Care Limited | Haverton Recruitment And Staffing | Planning estimate for discussion with your accountant
A3: Change the yellow cells only. All amounts exclude VAT. Figures are estimates, not verified results.
A5: Input | B5: Value | C5: Notes
A6: First week of supply (Monday) | B6: 46482 | C6: Earliest realistic pilot date after the Go Live Gate. Change to your date.
A7: Opening cash available for temporary staffing (£) | B7: 10000 | C7: [confirm] Cash you can set aside. Keep it separate from other business cash.
A8: Worker pay rate per hour (£) | B8: 14.5 | C8: Must be at least the National Living Wage (£12.71 for 21+ from April 2026). Check local market rates.
A9: Charge rate to client per hour (£, ex VAT) | B9: 26 | C9: Weekday day rate. Nights, weekends and bank holidays should be charged higher.
A10: Hours per worker per week | B10: 30 | C10: Average hours actually worked and billed.
A11: Holiday pay accrual | B11: 0.1207 | C11: 12.07% of pay is the usual accrual for irregular-hours workers.
A12: Employer National Insurance (planning load) | B12: 0.105 | C12: Blended planning figure, not the statutory calculation. Your payroll will calculate the exact amount.
A13: Employer pension (planning load) | B13: 0.025 | C13: Auto-enrolment minimum employer contribution is 3% of qualifying earnings.
A14: Other cost per hour worked (£) | B14: 0.75 | C14: DBS, training, PPE, payroll software, per hour worked.
A15: Fixed weekly overheads for temporary staffing (£) | B15: 400 | C15: [confirm] Insurance, on-call phone, software, compliance checks. Replace with real quotes.
A16: Client payment terms (days) | B16: 7 | C16: Invoices go out weekly. Your plan is 7-day terms.
A17: Extra delay if clients pay late (weeks) | B17: 0 | C17: Stress test: set to 2 or 4 to see the effect of late payers.
A19: Margin check per hour
A20: Loaded cost per hour (£) | B20: =B8*(1+B11+B12+B13)+B14 -> 18.88515
A21: Gross profit per hour (£) | B21: =B9-B20 -> 7.11485
A22: Gross margin | B22: =IF(B9=0,0,B21/B9) -> 0.27364808
A23: Meets Haverton floor (£5.50 per hour and 20%)? | B23: =IF(AND(B21>=5.5,B22>=0.2),"Yes","No: needs Director approval") -> Yes
A24: Weeks between work and payment | B24: =1+ROUNDUP(B16/7,0)+B17 -> 2
A26: Results
A27: Lowest cash balance in 13 weeks (£) | B27: =MIN('Cash Flow'!L3:L15) -> 7378.237
A28: Extra funding needed to stay above £0 (£) | B28: =MAX(0,-B27) -> 0
A29: Week with lowest balance | B29: =INDEX('Cash Flow'!A3:A15,MATCH(B27,'Cash Flow'!L3:L15,0)) -> 6
A30: Unpaid client invoices at end of week 13 (£) | B30: =SUM('Cash Flow'!E3:E15)-SUM('Cash Flow'!F3:F15) -> 9360
A31: Gross profit earned over 13 weeks (£) | B31: =SUM('Cash Flow'!E3:E15)-SUM('Cash Flow'!G3:G15)-SUM('Cash Flow'!H3:H15) -> 12379.839
A33: How to read this
A34: You pay workers every week, one week in arrears. Clients pay you later. The gap is the cash you need.
A35: Wages, holiday pay, National Insurance and pension are treated as paid with each weekly payroll. HMRC and pension payments are usually monthly, so this is slightly cautious.
A36: VAT is left out. If you are VAT registered, the VAT you collect belongs to HMRC and must not be used to pay wages.
A37: Ask your accountant to check this before you commit to any client. If the "Extra funding needed" cell is red, arrange funding (for example invoice finance) before the pilot.

Sheet Cash Flow
A1: Weekly cash flow (change workers in the yellow column)
A2: Week | B2: Week starting | C2: Workers on shift | D2: Hours billed | E2: Invoiced to clients (£) | F2: Cash in from clients (£) | G2: Wage cost incurred (£) | H2: Other costs (£) | I2: Wages paid this week (£) | J2: Fixed overheads (£) | K2: Cash out total (£) | L2: Closing cash (£)
A3: 1 | B3: =Inputs!$B$6+7*(A3-1) -> 46482 | C3: 2 | D3: =C3*Inputs!$B$10 -> 60 | E3: =D3*Inputs!$B$9 -> 1560 | F3: =IF(A3-Inputs!$B$24>=1,INDEX($E$3:$E$15,A3-Inputs!$B$24),0) -> 0 | G3: =D3*Inputs!$B$8*(1+Inputs!$B$11+Inputs!$B$12+Inputs!$B$13) -> 1088.109 | H3: =D3*Inputs!$B$14 -> 45 | I3: 0 | J3: =Inputs!$B$15 -> 400 | K3: =H3+I3+J3 -> 445 | L3: =Inputs!$B$7+F3-K3 -> 9555
A4: 2 | B4: =Inputs!$B$6+7*(A4-1) -> 46489 | C4: 2 | D4: =C4*Inputs!$B$10 -> 60 | E4: =D4*Inputs!$B$9 -> 1560 | F4: =IF(A4-Inputs!$B$24>=1,INDEX($E$3:$E$15,A4-Inputs!$B$24),0) -> 0 | G4: =D4*Inputs!$B$8*(1+Inputs!$B$11+Inputs!$B$12+Inputs!$B$13) -> 1088.109 | H4: =D4*Inputs!$B$14 -> 45 | I4: =G3 -> 1088.109 | J4: =Inputs!$B$15 -> 400 | K4: =H4+I4+J4 -> 1533.109 | L4: =L3+F4-K4 -> 8021.891
A5: 3 | B5: =Inputs!$B$6+7*(A5-1) -> 46496 | C5: 3 | D5: =C5*Inputs!$B$10 -> 90 | E5: =D5*Inputs!$B$9 -> 2340 | F5: =IF(A5-Inputs!$B$24>=1,INDEX($E$3:$E$15,A5-Inputs!$B$24),0) -> 1560 | G5: =D5*Inputs!$B$8*(1+Inputs!$B$11+Inputs!$B$12+Inputs!$B$13) -> 1632.1635 | H5: =D5*Inputs!$B$14 -> 67.5 | I5: =G4 -> 1088.109 | J5: =Inputs!$B$15 -> 400 | K5: =H5+I5+J5 -> 1555.609 | L5: =L4+F5-K5 -> 8026.282
A6: 4 | B6: =Inputs!$B$6+7*(A6-1) -> 46503 | C6: 3 | D6: =C6*Inputs!$B$10 -> 90 | E6: =D6*Inputs!$B$9 -> 2340 | F6: =IF(A6-Inputs!$B$24>=1,INDEX($E$3:$E$15,A6-Inputs!$B$24),0) -> 1560 | G6: =D6*Inputs!$B$8*(1+Inputs!$B$11+Inputs!$B$12+Inputs!$B$13) -> 1632.1635 | H6: =D6*Inputs!$B$14 -> 67.5 | I6: =G5 -> 1632.1635 | J6: =Inputs!$B$15 -> 400 | K6: =H6+I6+J6 -> 2099.6635 | L6: =L5+F6-K6 -> 7486.6185
A7: 5 | B7: =Inputs!$B$6+7*(A7-1) -> 46510 | C7: 4 | D7: =C7*Inputs!$B$10 -> 120 | E7: =D7*Inputs!$B$9 -> 3120 | F7: =IF(A7-Inputs!$B$24>=1,INDEX($E$3:$E$15,A7-Inputs!$B$24),0) -> 2340 | G7: =D7*Inputs!$B$8*(1+Inputs!$B$11+Inputs!$B$12+Inputs!$B$13) -> 2176.218 | H7: =D7*Inputs!$B$14 -> 90 | I7: =G6 -> 1632.1635 | J7: =Inputs!$B$15 -> 400 | K7: =H7+I7+J7 -> 2122.1635 | L7: =L6+F7-K7 -> 7704.455
A8: 6 | B8: =Inputs!$B$6+7*(A8-1) -> 46517 | C8: 4 | D8: =C8*Inputs!$B$10 -> 120 | E8: =D8*Inputs!$B$9 -> 3120 | F8: =IF(A8-Inputs!$B$24>=1,INDEX($E$3:$E$15,A8-Inputs!$B$24),0) -> 2340 | G8: =D8*Inputs!$B$8*(1+Inputs!$B$11+Inputs!$B$12+Inputs!$B$13) -> 2176.218 | H8: =D8*Inputs!$B$14 -> 90 | I8: =G7 -> 2176.218 | J8: =Inputs!$B$15 -> 400 | K8: =H8+I8+J8 -> 2666.218 | L8: =L7+F8-K8 -> 7378.237
A9: 7 | B9: =Inputs!$B$6+7*(A9-1) -> 46524 | C9: 5 | D9: =C9*Inputs!$B$10 -> 150 | E9: =D9*Inputs!$B$9 -> 3900 | F9: =IF(A9-Inputs!$B$24>=1,INDEX($E$3:$E$15,A9-Inputs!$B$24),0) -> 3120 | G9: =D9*Inputs!$B$8*(1+Inputs!$B$11+Inputs!$B$12+Inputs!$B$13) -> 2720.2725 | H9: =D9*Inputs!$B$14 -> 112.5 | I9: =G8 -> 2176.218 | J9: =Inputs!$B$15 -> 400 | K9: =H9+I9+J9 -> 2688.718 | L9: =L8+F9-K9 -> 7809.519
A10: 8 | B10: =Inputs!$B$6+7*(A10-1) -> 46531 | C10: 5 | D10: =C10*Inputs!$B$10 -> 150 | E10: =D10*Inputs!$B$9 -> 3900 | F10: =IF(A10-Inputs!$B$24>=1,INDEX($E$3:$E$15,A10-Inputs!$B$24),0) -> 3120 | G10: =D10*Inputs!$B$8*(1+Inputs!$B$11+Inputs!$B$12+Inputs!$B$13) -> 2720.2725 | H10: =D10*Inputs!$B$14 -> 112.5 | I10: =G9 -> 2720.2725 | J10: =Inputs!$B$15 -> 400 | K10: =H10+I10+J10 -> 3232.7725 | L10: =L9+F10-K10 -> 7696.7465
A11: 9 | B11: =Inputs!$B$6+7*(A11-1) -> 46538 | C11: 6 | D11: =C11*Inputs!$B$10 -> 180 | E11: =D11*Inputs!$B$9 -> 4680 | F11: =IF(A11-Inputs!$B$24>=1,INDEX($E$3:$E$15,A11-Inputs!$B$24),0) -> 3900 | G11: =D11*Inputs!$B$8*(1+Inputs!$B$11+Inputs!$B$12+Inputs!$B$13) -> 3264.327 | H11: =D11*Inputs!$B$14 -> 135 | I11: =G10 -> 2720.2725 | J11: =Inputs!$B$15 -> 400 | K11: =H11+I11+J11 -> 3255.2725 | L11: =L10+F11-K11 -> 8341.474
A12: 10 | B12: =Inputs!$B$6+7*(A12-1) -> 46545 | C12: 6 | D12: =C12*Inputs!$B$10 -> 180 | E12: =D12*Inputs!$B$9 -> 4680 | F12: =IF(A12-Inputs!$B$24>=1,INDEX($E$3:$E$15,A12-Inputs!$B$24),0) -> 3900 | G12: =D12*Inputs!$B$8*(1+Inputs!$B$11+Inputs!$B$12+Inputs!$B$13) -> 3264.327 | H12: =D12*Inputs!$B$14 -> 135 | I12: =G11 -> 3264.327 | J12: =Inputs!$B$15 -> 400 | K12: =H12+I12+J12 -> 3799.327 | L12: =L11+F12-K12 -> 8442.147
A13: 11 | B13: =Inputs!$B$6+7*(A13-1) -> 46552 | C13: 6 | D13: =C13*Inputs!$B$10 -> 180 | E13: =D13*Inputs!$B$9 -> 4680 | F13: =IF(A13-Inputs!$B$24>=1,INDEX($E$3:$E$15,A13-Inputs!$B$24),0) -> 4680 | G13: =D13*Inputs!$B$8*(1+Inputs!$B$11+Inputs!$B$12+Inputs!$B$13) -> 3264.327 | H13: =D13*Inputs!$B$14 -> 135 | I13: =G12 -> 3264.327 | J13: =Inputs!$B$15 -> 400 | K13: =H13+I13+J13 -> 3799.327 | L13: =L12+F13-K13 -> 9322.82
A14: 12 | B14: =Inputs!$B$6+7*(A14-1) -> 46559 | C14: 6 | D14: =C14*Inputs!$B$10 -> 180 | E14: =D14*Inputs!$B$9 -> 4680 | F14: =IF(A14-Inputs!$B$24>=1,INDEX($E$3:$E$15,A14-Inputs!$B$24),0) -> 4680 | G14: =D14*Inputs!$B$8*(1+Inputs!$B$11+Inputs!$B$12+Inputs!$B$13) -> 3264.327 | H14: =D14*Inputs!$B$14 -> 135 | I14: =G13 -> 3264.327 | J14: =Inputs!$B$15 -> 400 | K14: =H14+I14+J14 -> 3799.327 | L14: =L13+F14-K14 -> 10203.493
A15: 13 | B15: =Inputs!$B$6+7*(A15-1) -> 46566 | C15: 6 | D15: =C15*Inputs!$B$10 -> 180 | E15: =D15*Inputs!$B$9 -> 4680 | F15: =IF(A15-Inputs!$B$24>=1,INDEX($E$3:$E$15,A15-Inputs!$B$24),0) -> 4680 | G15: =D15*Inputs!$B$8*(1+Inputs!$B$11+Inputs!$B$12+Inputs!$B$13) -> 3264.327 | H15: =D15*Inputs!$B$14 -> 135 | I15: =G14 -> 3264.327 | J15: =Inputs!$B$15 -> 400 | K15: =H15+I15+J15 -> 3799.327 | L15: =L14+F15-K15 -> 11084.166
A16: Total | D16: =SUM(D3:D15) -> 1740 | E16: =SUM(E3:E15) -> 45240 | F16: =SUM(F3:F15) -> 35880 | G16: =SUM(G3:G15) -> 31555.161 | H16: =SUM(H3:H15) -> 1305 | I16: =SUM(I3:I15) -> 28290.834 | J16: =SUM(J3:J15) -> 5200 | K16: =SUM(K3:K15) -> 34795.834
A18: Wages for the final week (week 13) are paid in week 14, so they do not appear here. Workers must be paid even if a client pays late or not at all (Conduct Regulations, regulation 12).
